qss_parser/__init__.py
qss_parser/qss_parser.py
qss_parser-0.2.1.dist-info/licenses/LICENSE.md
qss_parser-0.2.1.dist-info/METADATA
qss_parser-0.2.1.dist-info/WHEEL
qss_parser-0.2.1.dist-info/top_level.txt
qss_parser-0.2.1.dist-info/RECORD
