Metadata-Version: 2.4
Name: qss-parser
Version: 0.2.1
Summary: A parser Python to Qt Style Sheets (QSS)
Author-email: Onimock <onimock@gmail.com>
Project-URL: Homepage, https://github.com/OniMock/qss_parser
Project-URL: Bug Tracker, https://github.com/OniMock/qss_parser/issues
Classifier: Programming Language :: Python :: 3
Classifier: License :: OSI Approved :: MIT License
Classifier: Operating System :: OS Independent
Requires-Python: >=3.6
License-File: LICENSE.md
Dynamic: license-file
